radium/__init__.py
radium/equity/__init__.py
radium/equity/_daily.py
radium/equity/equity.py
radium/helpers/__init__.py
radium/helpers/_convert_date.py
radium/helpers/_truncate.py
radium/pair/__init__.py
radium/pair/cadf_test.py
radium/pair/johansen_test.py
radium/pair/pair.py
radium/strategy/__init__.py
radium/strategy/_returns.py
radium/strategy/bollinger_pair.py
radium/strategy/pair_strategy.py
radium/strategy/strategy.py
Radium_Tech-0.1.0.dist-info/LICENSE
Radium_Tech-0.1.0.dist-info/METADATA
Radium_Tech-0.1.0.dist-info/WHEEL
Radium_Tech-0.1.0.dist-info/entry_points.txt
Radium_Tech-0.1.0.dist-info/top_level.txt
Radium_Tech-0.1.0.dist-info/RECORD
